{
    "Timestamp_experience": "0.575999975",
    "Timestamp_local": "2018-Jul-18 15:37:22"
}
{
    "Timestamp_experience": "0.656000018",
    "Timestamp_local": "2018-Jul-18 15:37:22"
}
{
    "Timestamp_experience": "0.689999998",
    "Timestamp_local": "2018-Jul-18 15:37:22"
}
{
    "Timestamp_experience": "0.723999977",
    "Timestamp_local": "2018-Jul-18 15:37:22"
}
{
    "Timestamp_experience": "0.79400003",
    "Timestamp_local": "2018-Jul-18 15:37:22"
}
{
    "Timestamp_experience": "0.842000008",
    "Timestamp_local": "2018-Jul-18 15:37:23"
}
{
    "Timestamp_experience": "0.89200002",
    "Timestamp_local": "2018-Jul-18 15:37:23"
}
{
    "Timestamp_experience": "0.958999991",
    "Timestamp_local": "2018-Jul-18 15:37:23"
}
{
    "Timestamp_experience": "1.023",
    "Timestamp_local": "2018-Jul-18 15:37:23"
}
{
    "Timestamp_experience": "1.08399999",
    "Timestamp_local": "2018-Jul-18 15:37:23"
}
{
    "Timestamp_experience": "1.13999999",
    "Timestamp_local": "2018-Jul-18 15:37:23"
}
{
    "Timestamp_experience": "1.18700004",
    "Timestamp_local": "2018-Jul-18 15:37:23"
}
{
    "Timestamp_experience": "1.23300004",
    "Timestamp_local": "2018-Jul-18 15:37:23"
}
{
    "Timestamp_experience": "1.28799999",
    "Timestamp_local": "2018-Jul-18 15:37:23"
}
{
    "Timestamp_experience": "1.34500003",
    "Timestamp_local": "2018-Jul-18 15:37:23"
}
{
    "Timestamp_experience": "1.39699996",
    "Timestamp_local": "2018-Jul-18 15:37:23"
}
{
    "Timestamp_experience": "1.46000004",
    "Timestamp_local": "2018-Jul-18 15:37:23"
}
{
    "Timestamp_experience": "1.52199996",
    "Timestamp_local": "2018-Jul-18 15:37:23"
}
{
    "Timestamp_experience": "1.58200002",
    "Timestamp_local": "2018-Jul-18 15:37:23"
}
{
    "Timestamp_experience": "1.648",
    "Timestamp_local": "2018-Jul-18 15:37:23"
}
{
    "Timestamp_experience": "1.70599997",
    "Timestamp_local": "2018-Jul-18 15:37:23"
}
{
    "Timestamp_experience": "1.74699998",
    "Timestamp_local": "2018-Jul-18 15:37:23"
}
{
    "Timestamp_experience": "1.796",
    "Timestamp_local": "2018-Jul-18 15:37:24"
}
{
    "Timestamp_experience": "1.86300004",
    "Timestamp_local": "2018-Jul-18 15:37:24"
}
{
    "Timestamp_experience": "1.92799997",
    "Timestamp_local": "2018-Jul-18 15:37:24"
}
{
    "Timestamp_experience": "1.98800004",
    "Timestamp_local": "2018-Jul-18 15:37:24"
}
{
    "Timestamp_experience": "2.05200005",
    "Timestamp_local": "2018-Jul-18 15:37:24"
}
{
    "Timestamp_experience": "2.11800003",
    "Timestamp_local": "2018-Jul-18 15:37:24"
}
{
    "Timestamp_experience": "2.17600012",
    "Timestamp_local": "2018-Jul-18 15:37:24"
}
{
    "Timestamp_experience": "2.23399997",
    "Timestamp_local": "2018-Jul-18 15:37:24"
}
{
    "Timestamp_experience": "2.2809999",
    "Timestamp_local": "2018-Jul-18 15:37:24"
}
{
    "Timestamp_experience": "2.32800007",
    "Timestamp_local": "2018-Jul-18 15:37:24"
}
{
    "Timestamp_experience": "2.37899995",
    "Timestamp_local": "2018-Jul-18 15:37:24"
}
{
    "Timestamp_experience": "2.44300008",
    "Timestamp_local": "2018-Jul-18 15:37:24"
}
{
    "Timestamp_experience": "2.50699997",
    "Timestamp_local": "2018-Jul-18 15:37:24"
}
{
    "Timestamp_experience": "2.56500006",
    "Timestamp_local": "2018-Jul-18 15:37:24"
}
{
    "Timestamp_experience": "2.62899995",
    "Timestamp_local": "2018-Jul-18 15:37:24"
}
{
    "Timestamp_experience": "2.69400001",
    "Timestamp_local": "2018-Jul-18 15:37:24"
}
{
    "Timestamp_experience": "2.75099993",
    "Timestamp_local": "2018-Jul-18 15:37:24"
}
{
    "Timestamp_experience": "2.79299998",
    "Timestamp_local": "2018-Jul-18 15:37:24"
}
{
    "Timestamp_experience": "2.84299994",
    "Timestamp_local": "2018-Jul-18 15:37:25"
}
{
    "Timestamp_experience": "2.89899993",
    "Timestamp_local": "2018-Jul-18 15:37:25"
}
{
    "Timestamp_experience": "2.95900011",
    "Timestamp_local": "2018-Jul-18 15:37:25"
}
{
    "Timestamp_experience": "3.01600003",
    "Timestamp_local": "2018-Jul-18 15:37:25"
}
{
    "Timestamp_experience": "3.08999991",
    "Timestamp_local": "2018-Jul-18 15:37:25"
}
{
    "Timestamp_experience": "3.14499998",
    "Timestamp_local": "2018-Jul-18 15:37:25"
}
{
    "Timestamp_experience": "3.20300007",
    "Timestamp_local": "2018-Jul-18 15:37:25"
}
{
    "Timestamp_experience": "3.25500011",
    "Timestamp_local": "2018-Jul-18 15:37:25"
}
{
    "Timestamp_experience": "3.31100011",
    "Timestamp_local": "2018-Jul-18 15:37:25"
}
{
    "Timestamp_experience": "3.35899997",
    "Timestamp_local": "2018-Jul-18 15:37:25"
}
{
    "Timestamp_experience": "3.41100001",
    "Timestamp_local": "2018-Jul-18 15:37:25"
}
{
    "Timestamp_experience": "3.4749999",
    "Timestamp_local": "2018-Jul-18 15:37:25"
}
{
    "Timestamp_experience": "3.53999996",
    "Timestamp_local": "2018-Jul-18 15:37:25"
}
{
    "Timestamp_experience": "3.5999999",
    "Timestamp_local": "2018-Jul-18 15:37:25"
}
{
    "Timestamp_experience": "3.66100001",
    "Timestamp_local": "2018-Jul-18 15:37:25"
}
{
    "Timestamp_experience": "3.7249999",
    "Timestamp_local": "2018-Jul-18 15:37:25"
}
{
    "Timestamp_experience": "3.79200006",
    "Timestamp_local": "2018-Jul-18 15:37:25"
}
{
    "Timestamp_experience": "3.84200001",
    "Timestamp_local": "2018-Jul-18 15:37:26"
}
{
    "Timestamp_experience": "3.89299989",
    "Timestamp_local": "2018-Jul-18 15:37:26"
}
{
    "Timestamp_experience": "3.96099997",
    "Timestamp_local": "2018-Jul-18 15:37:26"
}
{
    "Timestamp_experience": "4.01900005",
    "Timestamp_local": "2018-Jul-18 15:37:26"
}
{
    "Timestamp_experience": "4.08599997",
    "Timestamp_local": "2018-Jul-18 15:37:26"
}
{
    "Timestamp_experience": "4.14699984",
    "Timestamp_local": "2018-Jul-18 15:37:26"
}
{
    "Timestamp_experience": "4.204",
    "Timestamp_local": "2018-Jul-18 15:37:26"
}
{
    "Timestamp_experience": "4.25500011",
    "Timestamp_local": "2018-Jul-18 15:37:26"
}
{
    "Timestamp_experience": "4.3130002",
    "Timestamp_local": "2018-Jul-18 15:37:26"
}
{
    "Timestamp_experience": "4.35900021",
    "Timestamp_local": "2018-Jul-18 15:37:26"
}
{
    "Timestamp_experience": "4.40500021",
    "Timestamp_local": "2018-Jul-18 15:37:26"
}
{
    "Timestamp_experience": "4.45900011",
    "Timestamp_local": "2018-Jul-18 15:37:26"
}
{
    "Timestamp_experience": "4.52400017",
    "Timestamp_local": "2018-Jul-18 15:37:26"
}
{
    "Timestamp_experience": "4.59299994",
    "Timestamp_local": "2018-Jul-18 15:37:26"
}
{
    "Timestamp_experience": "4.63899994",
    "Timestamp_local": "2018-Jul-18 15:37:26"
}
{
    "Timestamp_experience": "4.69299984",
    "Timestamp_local": "2018-Jul-18 15:37:26"
}
{
    "Timestamp_experience": "4.75899982",
    "Timestamp_local": "2018-Jul-18 15:37:26"
}
{
    "Timestamp_experience": "4.8210001",
    "Timestamp_local": "2018-Jul-18 15:37:27"
}
{
    "Timestamp_experience": "4.87699986",
    "Timestamp_local": "2018-Jul-18 15:37:27"
}
{
    "Timestamp_experience": "4.94399977",
    "Timestamp_local": "2018-Jul-18 15:37:27"
}
{
    "Timestamp_experience": "5.00899982",
    "Timestamp_local": "2018-Jul-18 15:37:27"
}
{
    "Timestamp_experience": "5.06699991",
    "Timestamp_local": "2018-Jul-18 15:37:27"
}
{
    "Timestamp_experience": "5.13399982",
    "Timestamp_local": "2018-Jul-18 15:37:27"
}
{
    "Timestamp_experience": "5.19299984",
    "Timestamp_local": "2018-Jul-18 15:37:27"
}
{
    "Timestamp_experience": "5.24800014",
    "Timestamp_local": "2018-Jul-18 15:37:27"
}
{
    "Timestamp_experience": "5.3039999",
    "Timestamp_local": "2018-Jul-18 15:37:27"
}
{
    "Timestamp_experience": "5.36199999",
    "Timestamp_local": "2018-Jul-18 15:37:27"
}
{
    "Timestamp_experience": "5.40500021",
    "Timestamp_local": "2018-Jul-18 15:37:27"
}
{
    "Timestamp_experience": "5.45300007",
    "Timestamp_local": "2018-Jul-18 15:37:27"
}
{
    "Timestamp_experience": "5.50600004",
    "Timestamp_local": "2018-Jul-18 15:37:27"
}
{
    "Timestamp_experience": "5.57200003",
    "Timestamp_local": "2018-Jul-18 15:37:27"
}
{
    "Timestamp_experience": "5.62900019",
    "Timestamp_local": "2018-Jul-18 15:37:27"
}
{
    "Timestamp_experience": "5.69299984",
    "Timestamp_local": "2018-Jul-18 15:37:27"
}
{
    "Timestamp_experience": "5.75699997",
    "Timestamp_local": "2018-Jul-18 15:37:27"
}
{
    "Timestamp_experience": "5.81799984",
    "Timestamp_local": "2018-Jul-18 15:37:28"
}
{
    "Timestamp_experience": "5.87200022",
    "Timestamp_local": "2018-Jul-18 15:37:28"
}
{
    "Timestamp_experience": "5.92299986",
    "Timestamp_local": "2018-Jul-18 15:37:28"
}
{
    "Timestamp_experience": "5.97700024",
    "Timestamp_local": "2018-Jul-18 15:37:28"
}
{
    "Timestamp_experience": "6.03599977",
    "Timestamp_local": "2018-Jul-18 15:37:28"
}
{
    "Timestamp_experience": "6.10099983",
    "Timestamp_local": "2018-Jul-18 15:37:28"
}
{
    "Timestamp_experience": "6.16699982",
    "Timestamp_local": "2018-Jul-18 15:37:28"
}
{
    "Timestamp_experience": "6.22800016",
    "Timestamp_local": "2018-Jul-18 15:37:28"
}
{
    "Timestamp_experience": "6.29199982",
    "Timestamp_local": "2018-Jul-18 15:37:28"
}
{
    "Timestamp_experience": "6.35300016",
    "Timestamp_local": "2018-Jul-18 15:37:28"
}
{
    "Timestamp_experience": "6.41099977",
    "Timestamp_local": "2018-Jul-18 15:37:28"
}
{
    "Timestamp_experience": "6.46899986",
    "Timestamp_local": "2018-Jul-18 15:37:28"
}
{
    "Timestamp_experience": "6.52400017",
    "Timestamp_local": "2018-Jul-18 15:37:28"
}
{
    "Timestamp_experience": "6.58599997",
    "Timestamp_local": "2018-Jul-18 15:37:28"
}
{
    "Timestamp_experience": "6.6420002",
    "Timestamp_local": "2018-Jul-18 15:37:28"
}
{
    "Timestamp_experience": "6.70499992",
    "Timestamp_local": "2018-Jul-18 15:37:28"
}
{
    "Timestamp_experience": "6.77199984",
    "Timestamp_local": "2018-Jul-18 15:37:28"
}
{
    "Timestamp_experience": "6.83599997",
    "Timestamp_local": "2018-Jul-18 15:37:29"
}
{
    "Timestamp_experience": "6.90100002",
    "Timestamp_local": "2018-Jul-18 15:37:29"
}
{
    "Timestamp_experience": "6.95900011",
    "Timestamp_local": "2018-Jul-18 15:37:29"
}
{
    "Timestamp_experience": "7.0170002",
    "Timestamp_local": "2018-Jul-18 15:37:29"
}
{
    "Timestamp_experience": "7.06799984",
    "Timestamp_local": "2018-Jul-18 15:37:29"
}
{
    "Timestamp_experience": "7.13000011",
    "Timestamp_local": "2018-Jul-18 15:37:29"
}
{
    "Timestamp_experience": "7.19399977",
    "Timestamp_local": "2018-Jul-18 15:37:29"
}
{
    "Timestamp_experience": "7.2579999",
    "Timestamp_local": "2018-Jul-18 15:37:29"
}
{
    "Timestamp_experience": "7.32299995",
    "Timestamp_local": "2018-Jul-18 15:37:29"
}
{
    "Timestamp_experience": "7.38399982",
    "Timestamp_local": "2018-Jul-18 15:37:29"
}
{
    "Timestamp_experience": "7.44199991",
    "Timestamp_local": "2018-Jul-18 15:37:29"
}
{
    "Timestamp_experience": "7.49700022",
    "Timestamp_local": "2018-Jul-18 15:37:29"
}
{
    "Timestamp_experience": "7.54799986",
    "Timestamp_local": "2018-Jul-18 15:37:29"
}
{
    "Timestamp_experience": "7.61800003",
    "Timestamp_local": "2018-Jul-18 15:37:29"
}
{
    "Timestamp_experience": "7.67399979",
    "Timestamp_local": "2018-Jul-18 15:37:29"
}
{
    "Timestamp_experience": "7.7420001",
    "Timestamp_local": "2018-Jul-18 15:37:29"
}
{
    "Timestamp_experience": "7.8039999",
    "Timestamp_local": "2018-Jul-18 15:37:30"
}
{
    "Timestamp_experience": "7.87099981",
    "Timestamp_local": "2018-Jul-18 15:37:30"
}
{
    "Timestamp_experience": "7.92999983",
    "Timestamp_local": "2018-Jul-18 15:37:30"
}
{
    "Timestamp_experience": "7.99700022",
    "Timestamp_local": "2018-Jul-18 15:37:30"
}
{
    "Timestamp_experience": "8.05599976",
    "Timestamp_local": "2018-Jul-18 15:37:30"
}
{
    "Timestamp_experience": "8.10999966",
    "Timestamp_local": "2018-Jul-18 15:37:30"
}
{
    "Timestamp_experience": "8.15699959",
    "Timestamp_local": "2018-Jul-18 15:37:30"
}
{
    "Timestamp_experience": "8.22599983",
    "Timestamp_local": "2018-Jul-18 15:37:30"
}
{
    "Timestamp_experience": "8.28499985",
    "Timestamp_local": "2018-Jul-18 15:37:30"
}
{
    "Timestamp_experience": "8.34899998",
    "Timestamp_local": "2018-Jul-18 15:37:30"
}
{
    "Timestamp_experience": "8.41600037",
    "Timestamp_local": "2018-Jul-18 15:37:30"
}
{
    "Timestamp_experience": "8.47599983",
    "Timestamp_local": "2018-Jul-18 15:37:30"
}
{
    "Timestamp_experience": "8.52999973",
    "Timestamp_local": "2018-Jul-18 15:37:30"
}
{
    "Timestamp_experience": "8.57600021",
    "Timestamp_local": "2018-Jul-18 15:37:30"
}
{
    "Timestamp_experience": "8.63199997",
    "Timestamp_local": "2018-Jul-18 15:37:30"
}
{
    "Timestamp_experience": "8.69799995",
    "Timestamp_local": "2018-Jul-18 15:37:30"
}
{
    "Timestamp_experience": "8.75800037",
    "Timestamp_local": "2018-Jul-18 15:37:30"
}
{
    "Timestamp_experience": "8.82199955",
    "Timestamp_local": "2018-Jul-18 15:37:31"
}
{
    "Timestamp_experience": "8.88199997",
    "Timestamp_local": "2018-Jul-18 15:37:31"
}
{
    "Timestamp_experience": "8.94099998",
    "Timestamp_local": "2018-Jul-18 15:37:31"
}
{
    "Timestamp_experience": "9.01000023",
    "Timestamp_local": "2018-Jul-18 15:37:31"
}
{
    "Timestamp_experience": "9.07699966",
    "Timestamp_local": "2018-Jul-18 15:37:31"
}
{
    "Timestamp_experience": "9.125",
    "Timestamp_local": "2018-Jul-18 15:37:31"
}
{
    "Timestamp_experience": "9.17399979",
    "Timestamp_local": "2018-Jul-18 15:37:31"
}
{
    "Timestamp_experience": "9.22500038",
    "Timestamp_local": "2018-Jul-18 15:37:31"
}
{
    "Timestamp_experience": "9.29100037",
    "Timestamp_local": "2018-Jul-18 15:37:31"
}
{
    "Timestamp_experience": "9.35000038",
    "Timestamp_local": "2018-Jul-18 15:37:31"
}
{
    "Timestamp_experience": "9.41399956",
    "Timestamp_local": "2018-Jul-18 15:37:31"
}
{
    "Timestamp_experience": "9.48600006",
    "Timestamp_local": "2018-Jul-18 15:37:31"
}
{
    "Timestamp_experience": "9.55099964",
    "Timestamp_local": "2018-Jul-18 15:37:31"
}
{
    "Timestamp_experience": "9.61800003",
    "Timestamp_local": "2018-Jul-18 15:37:31"
}
{
    "Timestamp_experience": "9.68000031",
    "Timestamp_local": "2018-Jul-18 15:37:31"
}
{
    "Timestamp_experience": "9.73200035",
    "Timestamp_local": "2018-Jul-18 15:37:31"
}
{
    "Timestamp_experience": "9.78499985",
    "Timestamp_local": "2018-Jul-18 15:37:32"
}
{
    "Timestamp_experience": "9.85099983",
    "Timestamp_local": "2018-Jul-18 15:37:32"
}
{
    "Timestamp_experience": "9.91600037",
    "Timestamp_local": "2018-Jul-18 15:37:32"
}
{
    "Timestamp_experience": "9.97500038",
    "Timestamp_local": "2018-Jul-18 15:37:32"
}
{
    "Timestamp_experience": "10.0380001",
    "Timestamp_local": "2018-Jul-18 15:37:32"
}
{
    "Timestamp_experience": "10.1079998",
    "Timestamp_local": "2018-Jul-18 15:37:32"
}
{
    "Timestamp_experience": "10.1610003",
    "Timestamp_local": "2018-Jul-18 15:37:32"
}
{
    "Timestamp_experience": "10.2200003",
    "Timestamp_local": "2018-Jul-18 15:37:32"
}
{
    "Timestamp_experience": "10.2659998",
    "Timestamp_local": "2018-Jul-18 15:37:32"
}
{
    "Timestamp_experience": "10.3149996",
    "Timestamp_local": "2018-Jul-18 15:37:32"
}
{
    "Timestamp_experience": "10.3649998",
    "Timestamp_local": "2018-Jul-18 15:37:32"
}
{
    "Timestamp_experience": "10.4309998",
    "Timestamp_local": "2018-Jul-18 15:37:32"
}
{
    "Timestamp_experience": "10.4919996",
    "Timestamp_local": "2018-Jul-18 15:37:32"
}
{
    "Timestamp_experience": "10.5530005",
    "Timestamp_local": "2018-Jul-18 15:37:32"
}
{
    "Timestamp_experience": "10.618",
    "Timestamp_local": "2018-Jul-18 15:37:32"
}
{
    "Timestamp_experience": "10.6789999",
    "Timestamp_local": "2018-Jul-18 15:37:32"
}
{
    "Timestamp_experience": "10.7410002",
    "Timestamp_local": "2018-Jul-18 15:37:32"
}
{
    "Timestamp_experience": "10.7989998",
    "Timestamp_local": "2018-Jul-18 15:37:33"
}
{
    "Timestamp_experience": "10.8669996",
    "Timestamp_local": "2018-Jul-18 15:37:33"
}
{
    "Timestamp_experience": "10.9329996",
    "Timestamp_local": "2018-Jul-18 15:37:33"
}
{
    "Timestamp_experience": "10.9899998",
    "Timestamp_local": "2018-Jul-18 15:37:33"
}
{
    "Timestamp_experience": "11.0570002",
    "Timestamp_local": "2018-Jul-18 15:37:33"
}
{
    "Timestamp_experience": "11.1160002",
    "Timestamp_local": "2018-Jul-18 15:37:33"
}
{
    "Timestamp_experience": "11.1890001",
    "Timestamp_local": "2018-Jul-18 15:37:33"
}
{
    "Timestamp_experience": "11.2799997",
    "Timestamp_local": "2018-Jul-18 15:37:33"
}
{
    "Timestamp_experience": "11.3389997",
    "Timestamp_local": "2018-Jul-18 15:37:33"
}
{
    "Timestamp_experience": "11.3929996",
    "Timestamp_local": "2018-Jul-18 15:37:33"
}
{
    "Timestamp_experience": "11.4460001",
    "Timestamp_local": "2018-Jul-18 15:37:33"
}
{
    "Timestamp_experience": "11.5109997",
    "Timestamp_local": "2018-Jul-18 15:37:33"
}
{
    "Timestamp_experience": "11.5749998",
    "Timestamp_local": "2018-Jul-18 15:37:33"
}
{
    "Timestamp_experience": "11.6260004",
    "Timestamp_local": "2018-Jul-18 15:37:33"
}
{
    "Timestamp_experience": "11.6789999",
    "Timestamp_local": "2018-Jul-18 15:37:33"
}
{
    "Timestamp_experience": "11.7419996",
    "Timestamp_local": "2018-Jul-18 15:37:33"
}
{
    "Timestamp_experience": "11.8059998",
    "Timestamp_local": "2018-Jul-18 15:37:34"
}
{
    "Timestamp_experience": "11.8599997",
    "Timestamp_local": "2018-Jul-18 15:37:34"
}
{
    "Timestamp_experience": "11.9040003",
    "Timestamp_local": "2018-Jul-18 15:37:34"
}
{
    "Timestamp_experience": "11.9809999",
    "Timestamp_local": "2018-Jul-18 15:37:34"
}
{
    "Timestamp_experience": "12.0360003",
    "Timestamp_local": "2018-Jul-18 15:37:34"
}
{
    "Timestamp_experience": "12.1040001",
    "Timestamp_local": "2018-Jul-18 15:37:34"
}
{
    "Timestamp_experience": "12.1700001",
    "Timestamp_local": "2018-Jul-18 15:37:34"
}
{
    "Timestamp_experience": "12.2259998",
    "Timestamp_local": "2018-Jul-18 15:37:34"
}
{
    "Timestamp_experience": "12.2869997",
    "Timestamp_local": "2018-Jul-18 15:37:34"
}
{
    "Timestamp_experience": "12.3459997",
    "Timestamp_local": "2018-Jul-18 15:37:34"
}
{
    "Timestamp_experience": "12.4069996",
    "Timestamp_local": "2018-Jul-18 15:37:34"
}
{
    "Timestamp_experience": "12.474",
    "Timestamp_local": "2018-Jul-18 15:37:34"
}
{
    "Timestamp_experience": "12.5380001",
    "Timestamp_local": "2018-Jul-18 15:37:34"
}
{
    "Timestamp_experience": "12.6020002",
    "Timestamp_local": "2018-Jul-18 15:37:34"
}
{
    "Timestamp_experience": "12.6569996",
    "Timestamp_local": "2018-Jul-18 15:37:34"
}
{
    "Timestamp_experience": "12.7250004",
    "Timestamp_local": "2018-Jul-18 15:37:34"
}
{
    "Timestamp_experience": "12.7910004",
    "Timestamp_local": "2018-Jul-18 15:37:34"
}
{
    "Timestamp_experience": "12.8540001",
    "Timestamp_local": "2018-Jul-18 15:37:35"
}
{
    "Timestamp_experience": "12.9060001",
    "Timestamp_local": "2018-Jul-18 15:37:35"
}
{
    "Timestamp_experience": "12.9610004",
    "Timestamp_local": "2018-Jul-18 15:37:35"
}
{
    "Timestamp_experience": "13.0209999",
    "Timestamp_local": "2018-Jul-18 15:37:35"
}
{
    "Timestamp_experience": "13.0780001",
    "Timestamp_local": "2018-Jul-18 15:37:35"
}
{
    "Timestamp_experience": "13.1309996",
    "Timestamp_local": "2018-Jul-18 15:37:35"
}
{
    "Timestamp_experience": "13.198",
    "Timestamp_local": "2018-Jul-18 15:37:35"
}
{
    "Timestamp_experience": "13.2530003",
    "Timestamp_local": "2018-Jul-18 15:37:35"
}
{
    "Timestamp_experience": "13.3210001",
    "Timestamp_local": "2018-Jul-18 15:37:35"
}
{
    "Timestamp_experience": "13.3839998",
    "Timestamp_local": "2018-Jul-18 15:37:35"
}
{
    "Timestamp_experience": "13.4350004",
    "Timestamp_local": "2018-Jul-18 15:37:35"
}
{
    "Timestamp_experience": "13.4840002",
    "Timestamp_local": "2018-Jul-18 15:37:35"
}
{
    "Timestamp_experience": "13.5360003",
    "Timestamp_local": "2018-Jul-18 15:37:35"
}
{
    "Timestamp_experience": "13.6000004",
    "Timestamp_local": "2018-Jul-18 15:37:35"
}
{
    "Timestamp_experience": "13.6669998",
    "Timestamp_local": "2018-Jul-18 15:37:35"
}
{
    "Timestamp_experience": "13.724",
    "Timestamp_local": "2018-Jul-18 15:37:35"
}
{
    "Timestamp_experience": "13.7889996",
    "Timestamp_local": "2018-Jul-18 15:37:35"
}
{
    "Timestamp_experience": "13.8470001",
    "Timestamp_local": "2018-Jul-18 15:37:36"
}
{
    "Timestamp_experience": "13.9040003",
    "Timestamp_local": "2018-Jul-18 15:37:36"
}
{
    "Timestamp_experience": "13.96",
    "Timestamp_local": "2018-Jul-18 15:37:36"
}
{
    "Timestamp_experience": "14.0380001",
    "Timestamp_local": "2018-Jul-18 15:37:36"
}
{
    "Timestamp_experience": "14.1020002",
    "Timestamp_local": "2018-Jul-18 15:37:36"
}
{
    "Timestamp_experience": "14.1739998",
    "Timestamp_local": "2018-Jul-18 15:37:36"
}
{
    "Timestamp_experience": "14.25",
    "Timestamp_local": "2018-Jul-18 15:37:36"
}
{
    "Timestamp_experience": "14.3070002",
    "Timestamp_local": "2018-Jul-18 15:37:36"
}
{
    "Timestamp_experience": "14.3760004",
    "Timestamp_local": "2018-Jul-18 15:37:36"
}
{
    "Timestamp_experience": "14.448",
    "Timestamp_local": "2018-Jul-18 15:37:36"
}
{
    "Timestamp_experience": "14.5059996",
    "Timestamp_local": "2018-Jul-18 15:37:36"
}
{
    "Timestamp_experience": "14.5699997",
    "Timestamp_local": "2018-Jul-18 15:37:36"
}
{
    "Timestamp_experience": "14.6339998",
    "Timestamp_local": "2018-Jul-18 15:37:36"
}
{
    "Timestamp_experience": "14.691",
    "Timestamp_local": "2018-Jul-18 15:37:36"
}
{
    "Timestamp_experience": "14.7609997",
    "Timestamp_local": "2018-Jul-18 15:37:36"
}
{
    "Timestamp_experience": "14.8240004",
    "Timestamp_local": "2018-Jul-18 15:37:37"
}
{
    "Timestamp_experience": "14.8809996",
    "Timestamp_local": "2018-Jul-18 15:37:37"
}
{
    "Timestamp_experience": "14.9359999",
    "Timestamp_local": "2018-Jul-18 15:37:37"
}
{
    "Timestamp_experience": "14.9840002",
    "Timestamp_local": "2018-Jul-18 15:37:37"
}
{
    "Timestamp_experience": "15.0419998",
    "Timestamp_local": "2018-Jul-18 15:37:37"
}
{
    "Timestamp_experience": "15.0979996",
    "Timestamp_local": "2018-Jul-18 15:37:37"
}
{
    "Timestamp_experience": "15.1619997",
    "Timestamp_local": "2018-Jul-18 15:37:37"
}
{
    "Timestamp_experience": "15.2279997",
    "Timestamp_local": "2018-Jul-18 15:37:37"
}
{
    "Timestamp_experience": "15.2910004",
    "Timestamp_local": "2018-Jul-18 15:37:37"
}
{
    "Timestamp_experience": "15.3540001",
    "Timestamp_local": "2018-Jul-18 15:37:37"
}
{
    "Timestamp_experience": "15.415",
    "Timestamp_local": "2018-Jul-18 15:37:37"
}
{
    "Timestamp_experience": "15.474",
    "Timestamp_local": "2018-Jul-18 15:37:37"
}
{
    "Timestamp_experience": "15.5310001",
    "Timestamp_local": "2018-Jul-18 15:37:37"
}
{
    "Timestamp_experience": "15.5860004",
    "Timestamp_local": "2018-Jul-18 15:37:37"
}
{
    "Timestamp_experience": "15.6499996",
    "Timestamp_local": "2018-Jul-18 15:37:37"
}
{
    "Timestamp_experience": "15.7130003",
    "Timestamp_local": "2018-Jul-18 15:37:37"
}
{
    "Timestamp_experience": "15.7679996",
    "Timestamp_local": "2018-Jul-18 15:37:37"
}
{
    "Timestamp_experience": "15.8219995",
    "Timestamp_local": "2018-Jul-18 15:37:38"
}
{
    "Timestamp_experience": "15.8889999",
    "Timestamp_local": "2018-Jul-18 15:37:38"
}
{
    "Timestamp_experience": "15.9390001",
    "Timestamp_local": "2018-Jul-18 15:37:38"
}
{
    "Timestamp_experience": "16.0020008",
    "Timestamp_local": "2018-Jul-18 15:37:38"
}
{
    "Timestamp_experience": "16.0480003",
    "Timestamp_local": "2018-Jul-18 15:37:38"
}
{
    "Timestamp_experience": "16.0949993",
    "Timestamp_local": "2018-Jul-18 15:37:38"
}
{
    "Timestamp_experience": "16.1459999",
    "Timestamp_local": "2018-Jul-18 15:37:38"
}
{
    "Timestamp_experience": "16.2099991",
    "Timestamp_local": "2018-Jul-18 15:37:38"
}
{
    "Timestamp_experience": "16.2770004",
    "Timestamp_local": "2018-Jul-18 15:37:38"
}
{
    "Timestamp_experience": "16.3390007",
    "Timestamp_local": "2018-Jul-18 15:37:38"
}
{
    "Timestamp_experience": "16.4039993",
    "Timestamp_local": "2018-Jul-18 15:37:38"
}
{
    "Timestamp_experience": "16.4629993",
    "Timestamp_local": "2018-Jul-18 15:37:38"
}
{
    "Timestamp_experience": "16.5219994",
    "Timestamp_local": "2018-Jul-18 15:37:38"
}
{
    "Timestamp_experience": "16.5779991",
    "Timestamp_local": "2018-Jul-18 15:37:38"
}
{
    "Timestamp_experience": "16.6310005",
    "Timestamp_local": "2018-Jul-18 15:37:38"
}
{
    "Timestamp_experience": "16.6940002",
    "Timestamp_local": "2018-Jul-18 15:37:38"
}
{
    "Timestamp_experience": "16.7579994",
    "Timestamp_local": "2018-Jul-18 15:37:38"
}
{
    "Timestamp_experience": "16.8190002",
    "Timestamp_local": "2018-Jul-18 15:37:39"
}
{
    "Timestamp_experience": "16.882",
    "Timestamp_local": "2018-Jul-18 15:37:39"
}
{
    "Timestamp_experience": "16.948",
    "Timestamp_local": "2018-Jul-18 15:37:39"
}
{
    "Timestamp_experience": "16.9990005",
    "Timestamp_local": "2018-Jul-18 15:37:39"
}
{
    "Timestamp_experience": "17.0440006",
    "Timestamp_local": "2018-Jul-18 15:37:39"
}
{
    "Timestamp_experience": "17.0930004",
    "Timestamp_local": "2018-Jul-18 15:37:39"
}
{
    "Timestamp_experience": "17.1459999",
    "Timestamp_local": "2018-Jul-18 15:37:39"
}
{
    "Timestamp_experience": "17.2129993",
    "Timestamp_local": "2018-Jul-18 15:37:39"
}
{
    "Timestamp_experience": "17.2749996",
    "Timestamp_local": "2018-Jul-18 15:37:39"
}
{
    "Timestamp_experience": "17.3369999",
    "Timestamp_local": "2018-Jul-18 15:37:39"
}
{
    "Timestamp_experience": "17.3920002",
    "Timestamp_local": "2018-Jul-18 15:37:39"
}
{
    "Timestamp_experience": "17.4449997",
    "Timestamp_local": "2018-Jul-18 15:37:39"
}
{
    "Timestamp_experience": "17.5060005",
    "Timestamp_local": "2018-Jul-18 15:37:39"
}
{
    "Timestamp_experience": "17.5680008",
    "Timestamp_local": "2018-Jul-18 15:37:39"
}
{
    "Timestamp_experience": "17.625",
    "Timestamp_local": "2018-Jul-18 15:37:39"
}
{
    "Timestamp_experience": "17.6760006",
    "Timestamp_local": "2018-Jul-18 15:37:39"
}
{
    "Timestamp_experience": "17.7450008",
    "Timestamp_local": "2018-Jul-18 15:37:39"
}
{
    "Timestamp_experience": "17.7999992",
    "Timestamp_local": "2018-Jul-18 15:37:40"
}
{
    "Timestamp_experience": "17.8740005",
    "Timestamp_local": "2018-Jul-18 15:37:40"
}
{
    "Timestamp_experience": "17.9349995",
    "Timestamp_local": "2018-Jul-18 15:37:40"
}
{
    "Timestamp_experience": "18",
    "Timestamp_local": "2018-Jul-18 15:37:40"
}
{
    "Timestamp_experience": "18.0769997",
    "Timestamp_local": "2018-Jul-18 15:37:40"
}
{
    "Timestamp_experience": "18.1480007",
    "Timestamp_local": "2018-Jul-18 15:37:40"
}
{
    "Timestamp_experience": "18.2070007",
    "Timestamp_local": "2018-Jul-18 15:37:40"
}
{
    "Timestamp_experience": "18.323",
    "Timestamp_local": "2018-Jul-18 15:37:40"
}
{
    "Timestamp_experience": "18.3880005",
    "Timestamp_local": "2018-Jul-18 15:37:40"
}
{
    "Timestamp_experience": "18.4370003",
    "Timestamp_local": "2018-Jul-18 15:37:40"
}
{
    "Timestamp_experience": "18.4960003",
    "Timestamp_local": "2018-Jul-18 15:37:40"
}
{
    "Timestamp_experience": "18.5580006",
    "Timestamp_local": "2018-Jul-18 15:37:40"
}
{
    "Timestamp_experience": "18.618",
    "Timestamp_local": "2018-Jul-18 15:37:40"
}
{
    "Timestamp_experience": "18.6700001",
    "Timestamp_local": "2018-Jul-18 15:37:40"
}
{
    "Timestamp_experience": "18.7210007",
    "Timestamp_local": "2018-Jul-18 15:37:40"
}
{
    "Timestamp_experience": "18.7889996",
    "Timestamp_local": "2018-Jul-18 15:37:41"
}
{
    "Timestamp_experience": "18.8460007",
    "Timestamp_local": "2018-Jul-18 15:37:41"
}
{
    "Timestamp_experience": "18.9139996",
    "Timestamp_local": "2018-Jul-18 15:37:41"
}
{
    "Timestamp_experience": "18.9769993",
    "Timestamp_local": "2018-Jul-18 15:37:41"
}
{
    "Timestamp_experience": "19.0400009",
    "Timestamp_local": "2018-Jul-18 15:37:41"
}
{
    "Timestamp_experience": "19.1030006",
    "Timestamp_local": "2018-Jul-18 15:37:41"
}
{
    "Timestamp_experience": "19.1669998",
    "Timestamp_local": "2018-Jul-18 15:37:41"
}
{
    "Timestamp_experience": "19.2280006",
    "Timestamp_local": "2018-Jul-18 15:37:41"
}
{
    "Timestamp_experience": "19.2800007",
    "Timestamp_local": "2018-Jul-18 15:37:41"
}
{
    "Timestamp_experience": "19.3400002",
    "Timestamp_local": "2018-Jul-18 15:37:41"
}
{
    "Timestamp_experience": "19.3990002",
    "Timestamp_local": "2018-Jul-18 15:37:41"
}
{
    "Timestamp_experience": "19.4599991",
    "Timestamp_local": "2018-Jul-18 15:37:41"
}
{
    "Timestamp_experience": "19.5259991",
    "Timestamp_local": "2018-Jul-18 15:37:41"
}
{
    "Timestamp_experience": "19.5849991",
    "Timestamp_local": "2018-Jul-18 15:37:41"
}
{
    "Timestamp_experience": "19.6439991",
    "Timestamp_local": "2018-Jul-18 15:37:41"
}
{
    "Timestamp_experience": "19.7059994",
    "Timestamp_local": "2018-Jul-18 15:37:41"
}
{
    "Timestamp_experience": "19.7670002",
    "Timestamp_local": "2018-Jul-18 15:37:41"
}
{
    "Timestamp_experience": "19.8129997",
    "Timestamp_local": "2018-Jul-18 15:37:41"
}
{
    "Timestamp_experience": "19.8610001",
    "Timestamp_local": "2018-Jul-18 15:37:42"
}
{
    "Timestamp_experience": "19.9060001",
    "Timestamp_local": "2018-Jul-18 15:37:42"
}
{
    "Timestamp_experience": "19.9549999",
    "Timestamp_local": "2018-Jul-18 15:37:42"
}
{
    "Timestamp_experience": "20.0170002",
    "Timestamp_local": "2018-Jul-18 15:37:42"
}
{
    "Timestamp_experience": "20.0620003",
    "Timestamp_local": "2018-Jul-18 15:37:42"
}
{
    "Timestamp_experience": "20.1189995",
    "Timestamp_local": "2018-Jul-18 15:37:42"
}
{
    "Timestamp_experience": "20.1800003",
    "Timestamp_local": "2018-Jul-18 15:37:42"
}
{
    "Timestamp_experience": "20.2369995",
    "Timestamp_local": "2018-Jul-18 15:37:42"
}
{
    "Timestamp_experience": "20.2970009",
    "Timestamp_local": "2018-Jul-18 15:37:42"
}
{
    "Timestamp_experience": "20.3439999",
    "Timestamp_local": "2018-Jul-18 15:37:42"
}
{
    "Timestamp_experience": "20.4009991",
    "Timestamp_local": "2018-Jul-18 15:37:42"
}
{
    "Timestamp_experience": "20.4610004",
    "Timestamp_local": "2018-Jul-18 15:37:42"
}
{
    "Timestamp_experience": "20.5230007",
    "Timestamp_local": "2018-Jul-18 15:37:42"
}
{
    "Timestamp_experience": "20.5900002",
    "Timestamp_local": "2018-Jul-18 15:37:42"
}
{
    "Timestamp_experience": "20.6469994",
    "Timestamp_local": "2018-Jul-18 15:37:42"
}
{
    "Timestamp_experience": "20.7110004",
    "Timestamp_local": "2018-Jul-18 15:37:42"
}
{
    "Timestamp_experience": "20.7740002",
    "Timestamp_local": "2018-Jul-18 15:37:42"
}
{
    "Timestamp_experience": "20.8360004",
    "Timestamp_local": "2018-Jul-18 15:37:43"
}
{
    "Timestamp_experience": "20.8910007",
    "Timestamp_local": "2018-Jul-18 15:37:43"
}
{
    "Timestamp_experience": "20.9360008",
    "Timestamp_local": "2018-Jul-18 15:37:43"
}
{
    "Timestamp_experience": "21.0109997",
    "Timestamp_local": "2018-Jul-18 15:37:43"
}
{
    "Timestamp_experience": "21.0650005",
    "Timestamp_local": "2018-Jul-18 15:37:43"
}
{
    "Timestamp_experience": "21.1310005",
    "Timestamp_local": "2018-Jul-18 15:37:43"
}
{
    "Timestamp_experience": "21.1940002",
    "Timestamp_local": "2018-Jul-18 15:37:43"
}
{
    "Timestamp_experience": "21.2539997",
    "Timestamp_local": "2018-Jul-18 15:37:43"
}
{
    "Timestamp_experience": "21.3250008",
    "Timestamp_local": "2018-Jul-18 15:37:43"
}
{
    "Timestamp_experience": "21.3810005",
    "Timestamp_local": "2018-Jul-18 15:37:43"
}
{
    "Timestamp_experience": "21.4400005",
    "Timestamp_local": "2018-Jul-18 15:37:43"
}
{
    "Timestamp_experience": "21.4920006",
    "Timestamp_local": "2018-Jul-18 15:37:43"
}
{
    "Timestamp_experience": "21.5540009",
    "Timestamp_local": "2018-Jul-18 15:37:43"
}
{
    "Timestamp_experience": "21.6210003",
    "Timestamp_local": "2018-Jul-18 15:37:43"
}
{
    "Timestamp_experience": "21.6749992",
    "Timestamp_local": "2018-Jul-18 15:37:43"
}
{
    "Timestamp_experience": "21.7369995",
    "Timestamp_local": "2018-Jul-18 15:37:43"
}
{
    "Timestamp_experience": "21.802",
    "Timestamp_local": "2018-Jul-18 15:37:44"
}
{
    "Timestamp_experience": "21.868",
    "Timestamp_local": "2018-Jul-18 15:37:44"
}
{
    "Timestamp_experience": "21.9209995",
    "Timestamp_local": "2018-Jul-18 15:37:44"
}
{
    "Timestamp_experience": "21.9699993",
    "Timestamp_local": "2018-Jul-18 15:37:44"
}
{
    "Timestamp_experience": "22.0249996",
    "Timestamp_local": "2018-Jul-18 15:37:44"
}
{
    "Timestamp_experience": "22.0839996",
    "Timestamp_local": "2018-Jul-18 15:37:44"
}
{
    "Timestamp_experience": "22.1490002",
    "Timestamp_local": "2018-Jul-18 15:37:44"
}
{
    "Timestamp_experience": "22.2110004",
    "Timestamp_local": "2018-Jul-18 15:37:44"
}
{
    "Timestamp_experience": "22.2719994",
    "Timestamp_local": "2018-Jul-18 15:37:44"
}
{
    "Timestamp_experience": "22.3390007",
    "Timestamp_local": "2018-Jul-18 15:37:44"
}
{
    "Timestamp_experience": "22.3999996",
    "Timestamp_local": "2018-Jul-18 15:37:44"
}
{
    "Timestamp_experience": "22.4589996",
    "Timestamp_local": "2018-Jul-18 15:37:44"
}
{
    "Timestamp_experience": "22.5160007",
    "Timestamp_local": "2018-Jul-18 15:37:44"
}
{
    "Timestamp_experience": "22.5650005",
    "Timestamp_local": "2018-Jul-18 15:37:44"
}
{
    "Timestamp_experience": "22.6110001",
    "Timestamp_local": "2018-Jul-18 15:37:44"
}
{
    "Timestamp_experience": "22.6790009",
    "Timestamp_local": "2018-Jul-18 15:37:44"
}
{
    "Timestamp_experience": "22.7409992",
    "Timestamp_local": "2018-Jul-18 15:37:44"
}
{
    "Timestamp_experience": "22.7980003",
    "Timestamp_local": "2018-Jul-18 15:37:45"
}
{
    "Timestamp_experience": "22.8530006",
    "Timestamp_local": "2018-Jul-18 15:37:45"
}
{
    "Timestamp_experience": "22.9090004",
    "Timestamp_local": "2018-Jul-18 15:37:45"
}
{
    "Timestamp_experience": "22.9689999",
    "Timestamp_local": "2018-Jul-18 15:37:45"
}
{
    "Timestamp_experience": "23.0219994",
    "Timestamp_local": "2018-Jul-18 15:37:45"
}
{
    "Timestamp_experience": "23.0869999",
    "Timestamp_local": "2018-Jul-18 15:37:45"
}
{
    "Timestamp_experience": "23.1469994",
    "Timestamp_local": "2018-Jul-18 15:37:45"
}
{
    "Timestamp_experience": "23.2099991",
    "Timestamp_local": "2018-Jul-18 15:37:45"
}
{
    "Timestamp_experience": "23.2770004",
    "Timestamp_local": "2018-Jul-18 15:37:45"
}
{
    "Timestamp_experience": "23.3309994",
    "Timestamp_local": "2018-Jul-18 15:37:45"
}
{
    "Timestamp_experience": "23.3999996",
    "Timestamp_local": "2018-Jul-18 15:37:45"
}
{
    "Timestamp_experience": "23.4589996",
    "Timestamp_local": "2018-Jul-18 15:37:45"
}
{
    "Timestamp_experience": "23.5189991",
    "Timestamp_local": "2018-Jul-18 15:37:45"
}
{
    "Timestamp_experience": "23.5629997",
    "Timestamp_local": "2018-Jul-18 15:37:45"
}
{
    "Timestamp_experience": "23.6110001",
    "Timestamp_local": "2018-Jul-18 15:37:45"
}
{
    "Timestamp_experience": "23.6809998",
    "Timestamp_local": "2018-Jul-18 15:37:45"
}
{
    "Timestamp_experience": "23.7380009",
    "Timestamp_local": "2018-Jul-18 15:37:45"
}
{
    "Timestamp_experience": "23.7980003",
    "Timestamp_local": "2018-Jul-18 15:37:46"
}
{
    "Timestamp_experience": "23.8500004",
    "Timestamp_local": "2018-Jul-18 15:37:46"
}
{
    "Timestamp_experience": "23.9109993",
    "Timestamp_local": "2018-Jul-18 15:37:46"
}
{
    "Timestamp_experience": "23.9799995",
    "Timestamp_local": "2018-Jul-18 15:37:46"
}
{
    "Timestamp_experience": "24.0340004",
    "Timestamp_local": "2018-Jul-18 15:37:46"
}
{
    "Timestamp_experience": "24.0760002",
    "Timestamp_local": "2018-Jul-18 15:37:46"
}
{
    "Timestamp_experience": "24.125",
    "Timestamp_local": "2018-Jul-18 15:37:46"
}
{
    "Timestamp_experience": "24.1730003",
    "Timestamp_local": "2018-Jul-18 15:37:46"
}
{
    "Timestamp_experience": "24.2420006",
    "Timestamp_local": "2018-Jul-18 15:37:46"
}
{
    "Timestamp_experience": "24.309",
    "Timestamp_local": "2018-Jul-18 15:37:46"
}
{
    "Timestamp_experience": "24.3610001",
    "Timestamp_local": "2018-Jul-18 15:37:46"
}
{
    "Timestamp_experience": "24.4080009",
    "Timestamp_local": "2018-Jul-18 15:37:46"
}
{
    "Timestamp_experience": "24.4769993",
    "Timestamp_local": "2018-Jul-18 15:37:46"
}
{
    "Timestamp_experience": "24.5380001",
    "Timestamp_local": "2018-Jul-18 15:37:46"
}
{
    "Timestamp_experience": "24.5939999",
    "Timestamp_local": "2018-Jul-18 15:37:46"
}
{
    "Timestamp_experience": "24.6399994",
    "Timestamp_local": "2018-Jul-18 15:37:46"
}
{
    "Timestamp_experience": "24.6860008",
    "Timestamp_local": "2018-Jul-18 15:37:46"
}
{
    "Timestamp_experience": "24.7350006",
    "Timestamp_local": "2018-Jul-18 15:37:46"
}
{
    "Timestamp_experience": "24.7819996",
    "Timestamp_local": "2018-Jul-18 15:37:47"
}
{
    "Timestamp_experience": "24.8349991",
    "Timestamp_local": "2018-Jul-18 15:37:47"
}
{
    "Timestamp_experience": "24.9009991",
    "Timestamp_local": "2018-Jul-18 15:37:47"
}
{
    "Timestamp_experience": "24.9669991",
    "Timestamp_local": "2018-Jul-18 15:37:47"
}
{
    "Timestamp_experience": "25.0160007",
    "Timestamp_local": "2018-Jul-18 15:37:47"
}
{
    "Timestamp_experience": "25.0650005",
    "Timestamp_local": "2018-Jul-18 15:37:47"
}
{
    "Timestamp_experience": "25.1110001",
    "Timestamp_local": "2018-Jul-18 15:37:47"
}
{
    "Timestamp_experience": "25.1550007",
    "Timestamp_local": "2018-Jul-18 15:37:47"
}
{
    "Timestamp_experience": "25.2089996",
    "Timestamp_local": "2018-Jul-18 15:37:47"
}
{
    "Timestamp_experience": "25.2740002",
    "Timestamp_local": "2018-Jul-18 15:37:47"
}
{
    "Timestamp_experience": "25.3349991",
    "Timestamp_local": "2018-Jul-18 15:37:47"
}
{
    "Timestamp_experience": "25.3980007",
    "Timestamp_local": "2018-Jul-18 15:37:47"
}
{
    "Timestamp_experience": "25.4619999",
    "Timestamp_local": "2018-Jul-18 15:37:47"
}
